lineno/__init__.py
lineno/__main__.py
lineno/cli.py
lineno-0.3.0.dist-info/LICENSE
lineno-0.3.0.dist-info/METADATA
lineno-0.3.0.dist-info/WHEEL
lineno-0.3.0.dist-info/entry_points.txt
lineno-0.3.0.dist-info/top_level.txt
lineno-0.3.0.dist-info/RECORD
